libpyvinyl/AbstractBaseClass.py
libpyvinyl/BaseCalculator.py
libpyvinyl/BaseData.py
libpyvinyl/BaseFormat.py
libpyvinyl/Instrument.py
libpyvinyl/__init__.py
libpyvinyl/Parameters/Collections.py
libpyvinyl/Parameters/Parameter.py
libpyvinyl/Parameters/__init__.py
libpyvinyl-1.3.0.dist-info/LICENSE
libpyvinyl-1.3.0.dist-info/METADATA
libpyvinyl-1.3.0.dist-info/WHEEL
libpyvinyl-1.3.0.dist-info/top_level.txt
libpyvinyl-1.3.0.dist-info/RECORD
