Metadata-Version: 2.1
Name: libpyvinyl
Version: 1.3.0
Summary: The python API for photon and neutron simulation codes in the Photon and Neutron Open Science Cloud (PaNOSC).
Home-page: https://github.com/PaNOSC-ViNYL/libpyvinyl
Download-URL: https://github.com/PaNOSC-ViNYL/libpyvinyl/archive/v1.3.0.tar.gz
Author: Carsten Fortmann-Grote, Mads Bertelsen, Juncheng E, Shervin Nourbakhsh
Author-email: carsten.grote@xfel.eu, juncheng.e@xfel.eu, Mads.Bertelsen@ess.eu, nourbakhsh@ill.fr
License: LGPLv3
Keywords: photons,neutrons,simulations
Classifier: Development Status :: 3 - Alpha
Classifier: Intended Audience :: Developers
Classifier: Intended Audience :: Science/Research
Classifier: Topic :: Software Development :: Libraries :: Python Modules
Classifier: License :: OSI Approved :: GNU Lesser General Public License v3 or later (LGPLv3+)
Classifier: Programming Language :: Python :: 3
Classifier: Programming Language :: Python :: 3.6
Classifier: Programming Language :: Python :: 3.7
Classifier: Programming Language :: Python :: 3.8
Classifier: Programming Language :: Python :: 3.9
Classifier: Programming Language :: Python :: 3.10
License-File: LICENSE
Requires-Dist: pint
Requires-Dist: dill <=0.3.5.1
Requires-Dist: scipy
Requires-Dist: jsons
Requires-Dist: h5py
Requires-Dist: json-tricks
Requires-Dist: numpy
